lr_autotag/Foundation List 2.0.1.txt
lr_autotag/__init__.py
lr_autotag/cli.py
lr_autotag/tagger.py
lr_autotag-0.1.0.dist-info/METADATA
lr_autotag-0.1.0.dist-info/WHEEL
lr_autotag-0.1.0.dist-info/entry_points.txt
lr_autotag-0.1.0.dist-info/licenses/LICENSE.txt
lr_autotag-0.1.0.dist-info/RECORD
