Metadata-Version: 2.4
Name: lr-autotag
Version: 0.1.0
Summary: AI-powered keyword tagging assistant for Adobe Lightroom Classic
Author-email: Jsakkos <jonathansakkos@protonmail.com>
License: MIT
License-File: LICENSE.txt
Keywords: ai,clip,image,lightroom,photography,tagging
Classifier: Development Status :: 4 - Beta
Classifier: Intended Audience :: End Users/Desktop
Classifier: License :: OSI Approved :: MIT License
Classifier: Programming Language :: Python :: 3
Classifier: Programming Language :: Python :: 3.9
Classifier: Programming Language :: Python :: 3.10
Classifier: Programming Language :: Python :: 3.11
Classifier: Topic :: Multimedia :: Graphics
Requires-Python: >=3.9
Requires-Dist: click>=8.1.8
Requires-Dist: pillow>=11.0.0
Requires-Dist: torch>=2.5.1
Requires-Dist: transformers>=4.47.1
